submit_and_compare/__init__.py
submit_and_compare/models.py
submit_and_compare/settings.py
submit_and_compare/views.py
submit_and_compare/xblocks.py
submit_and_compare/mixins/__init__.py
submit_and_compare/mixins/dates.py
submit_and_compare/mixins/events.py
submit_and_compare/mixins/fragment.py
submit_and_compare/mixins/scenario.py
submit_and_compare/public/edit.js
submit_and_compare/public/view.css
submit_and_compare/public/view.js
submit_and_compare/public/view.less
submit_and_compare/scenarios/submit-and-compare-single.xml
submit_and_compare/templates/edit.html
submit_and_compare/templates/view.html
submit_and_compare/tests/__init__.py
submit_and_compare/tests/test_all.py
xblock_submit_and_compare-3.1.0.dist-info/LICENSE
xblock_submit_and_compare-3.1.0.dist-info/METADATA
xblock_submit_and_compare-3.1.0.dist-info/WHEEL
xblock_submit_and_compare-3.1.0.dist-info/entry_points.txt
xblock_submit_and_compare-3.1.0.dist-info/top_level.txt
xblock_submit_and_compare-3.1.0.dist-info/RECORD
