Metadata-Version: 2.1
Name: xblock-submit-and-compare
Version: 3.1.0
Summary: A submit-and-compare XBlock
Home-page: https://github.com/Stanford-Online/xblock-submit-and-compare
Author: stv
Author-email: stv@stanford.edu
License: AGPL-3.0
Classifier: Intended Audience :: Developers
Classifier: Intended Audience :: Education
Classifier: License :: OSI Approved :: GNU Affero General Public License v3
Classifier: Operating System :: OS Independent
Classifier: Programming Language :: JavaScript
Classifier: Programming Language :: Python
Classifier: Programming Language :: Python :: 3
Classifier: Programming Language :: Python :: 3.11
Classifier: Programming Language :: Python :: 3.12
Classifier: Framework :: Django
Classifier: Framework :: Django :: 4.2
Classifier: Framework :: Django :: 5.2
Classifier: Topic :: Education
Classifier: Topic :: Internet :: WWW/HTTP
License-File: LICENSE
Requires-Dist: Django
Requires-Dist: XBlock
Requires-Dist: six
